{
  "-MiBsknNSQ6aBG1-2lQS": {
    "Title": "bibulous",
    "Definition": "given to or marked by the consumption of alcohol",
    "Language": "English",
    "firebaseKey": "-MiBsknNSQ6aBG1-2lQS",
    "uid": "e6QOUG9KFmaCpJAJnEN5xseIbea2"
  },
  "-MiBuU13EaKmGOMjJF-X": {
    "Title": "tenebrous",
    "Definiton": "dark and gloomy",
    "Language": "English",
    "firebaseKey": "-MiBuU13EaKmGOMjJF-X",
    "uid": "e6QOUG9KFmaCpJAJnEN5xseIbea2"
  },
  "-MiBvEFJTI3FmTzDu_3V": {
    "Title": "myrmidon",
    "Definition": "a follower who carries out orders without question",
    "Language": "English",
    "firebaseKey": "-MiBvEFJTI3FmTzDu_3V",
    "uid": "e6QOUG9KFmaCpJAJnEN5xseIbea2"
  },
  "-MiBvW8ME_DvO2GzwQ8D": {
    "Title": "pule",
    "Definition": "cry weakly or softly",
    "Language": "English",
    "firebaseKey": "-MiBvW8ME_DvO2GzwQ8D",
    "uid": "e6QOUG9KFmaCpJAJnEN5xseIbea2"
  },
  "-MiBwAF5wOY00AYJm7cR": {
    "Title": "eschew",
    "Definition": "avoid and stay away from deliberately",
    "Language": "English",
    "firebaseKey": "-MiBwAF5wOY00AYJm7cR",
    "uid": "e6QOUG9KFmaCpJAJnEN5xseIbea2"
  },
  "-MiBvf3bIyooE6x4nLLB": {
    "Title": "junta",
    "Definition": "a group of officers who rule a country after seizing power",
    "Language": "English",
    "firebaseKey": "-MiBvf3bIyooE6x4nLLB",
    "uid": "e6QOUG9KFmaCpJAJnEN5xseIbea2"
  }
}
